nix_shell/__init__.py
nix_shell/_nix.py
nix_shell/builders.py
nix_shell/constants.py
nix_shell/exceptions.py
nix_shell/flake.py
nix_shell/nix_subprocess.py
nix_shell/nixlang.py
nix_shell/shell.py
nix_shell-0.0.3.dist-info/METADATA
nix_shell-0.0.3.dist-info/WHEEL
nix_shell-0.0.3.dist-info/RECORD
