Metadata-Version: 2.4
Name: nix-shell
Version: 0.0.3
Summary: Invoke reproducible Nix shells from Python.
Requires-Python: >=3.10
